cral/__init__.py
cral/version.py
cral/common.py
cral/metrics/__init__.py
cral/metrics/object_detection/__init__.py
cral/metrics/object_detection/utils.py
cral/metrics/object_detection/mAP_eval.py
cral/augmentations/engine.py
cral/augmentations/__init__.py
cral/data_feeder/semantic_seg_data_feeder.py
cral/data_feeder/parallel_data_feeder.py
cral/data_feeder/parse_dataset.py
cral/data_feeder/__init__.py
cral/data_feeder/classification_parallel_data_feeder.py
cral/data_feeder/utils.py
cral/data_feeder/object_detection_parser.py
cral/data_feeder/instance_seg_data_feeder.py
cral/data_feeder/classification_utils.py
cral/data_feeder/object_detection_parallel_data_feeder.py
cral/data_versioning/classification_data_parse_v2.py
cral/data_versioning/instanceSeg_data_parse_v2.py
cral/data_versioning/cral_hash.py
cral/data_versioning/segmentation_data_parse_v2.py
cral/data_versioning/__init__.py
cral/data_versioning/ObjectDetection_parse_data_v2.py
cral/data_versioning/cral_util.py
cral/models/__init__.py
cral/models/object_detection/__init__.py
cral/models/object_detection/object_detection_utils.py
cral/models/object_detection/FasterRCNN/fasterrcnn.py
cral/models/object_detection/FasterRCNN/tfrecord_parser.py
cral/models/object_detection/FasterRCNN/__init__.py
cral/models/object_detection/FasterRCNN/parsing_utils.py
cral/models/object_detection/FasterRCNN/utils.py
cral/models/object_detection/FasterRCNN/obj_det_utils.py
cral/models/object_detection/FasterRCNN/frcnn_utils.py
cral/models/object_detection/retinanet/tfrecord_parser.py
cral/models/object_detection/retinanet/base.py
cral/models/object_detection/retinanet/postprocessing.py
cral/models/object_detection/retinanet/predict_script.py
cral/models/object_detection/retinanet/__init__.py
cral/models/object_detection/retinanet/compute_overlap.cpython-36m-x86_64-linux-gnu.so
cral/models/object_detection/retinanet/utils.py
cral/models/object_detection/retinanet/preprocessing.py
cral-0.4.0.dist-info/WHEEL
cral-0.4.0.dist-info/LICENSE
cral-0.4.0.dist-info/RECORD
cral-0.4.0.dist-info/top_level.txt
cral-0.4.0.dist-info/METADATA
