Metadata-Version: 2.1
Name: cral
Version: 0.4.0
Summary: CRAL: Library for CNNs
Home-page: UNKNOWN
Author: T Pratik
Author-email: pratik@segmind.com
License: Apache License 2.0
Keywords: CNN,Deep Learning,classification,object detection,segmentation,keras,tensorflow-keras
Platform: UNKNOWN
Classifier: Intended Audience :: Developers
Classifier: Topic :: Scientific/Engineering :: Artificial Intelligence
Classifier: Programming Language :: Python :: 3.6
Requires-Dist: tqdm
Requires-Dist: xxhash
Requires-Dist: pandas
Requires-Dist: albumentations (==0.4.5)
Requires-Dist: jsonpickle
Requires-Dist: pycocotools
Requires-Dist: pydensecrf
